Metadata-Version: 1.2
Name: drmail
Version: 0.1.4
Summary: It's a simple email sending program
Home-page: UNKNOWN
Author: Judy
Author-email: ljd69154@liangjundi.cn
Maintainer: Judy
Maintainer-email: ljd69154@liangjundi.cn
License: GNU General Public License v3.0
Platform: all
Classifier: Operating System :: OS Independent
Classifier: License :: OSI Approved :: GNU General Public License v3 (GPLv3)
Classifier: Programming Language :: Python
Classifier: Programming Language :: Python :: Implementation
Classifier: Programming Language :: Python :: 3
